poetry_merge_lock/__init__.py
poetry_merge_lock/console.py
poetry_merge_lock/core.py
poetry_merge_lock/mergetool.py
poetry_merge_lock/parser.py
poetry_merge_lock-0.1.1.dist-info/entry_points.txt
poetry_merge_lock-0.1.1.dist-info/LICENSE
poetry_merge_lock-0.1.1.dist-info/WHEEL
poetry_merge_lock-0.1.1.dist-info/METADATA
poetry_merge_lock-0.1.1.dist-info/RECORD
