Metadata-Version: 2.1
Name: poetry-merge-lock
Version: 0.1.1
Summary: poetry-merge-lock
Home-page: https://github.com/cjolowicz/poetry-merge-lock
License: MIT
Author: Claudio Jolowicz
Author-email: mail@claudiojolowicz.com
Requires-Python: >=3.7,<4.0
Classifier: License :: OSI Approved :: MIT License
Classifier: Programming Language :: Python :: 3
Classifier: Programming Language :: Python :: 3.7
Classifier: Programming Language :: Python :: 3.8
Requires-Dist: click (>=7.0,<8.0)
Requires-Dist: importlib-metadata (>=1.1.3,<1.2.0); python_version < "3.8"
Requires-Dist: poetry (>=1.0.3,<2.0.0)
Requires-Dist: tomlkit (>=0.5.8,<0.6.0)
Project-URL: Documentation, https://poetry-merge-lock.readthedocs.io
Project-URL: Repository, https://github.com/cjolowicz/poetry-merge-lock
